mothpy/__init__.py
mothpy/bar_graphs_from_file.py
mothpy/bars.py
mothpy/carde_navigator.py
mothpy/casting_competition.py
mothpy/compare_navigators_in_different_wind_conditions.py
mothpy/demo_detection.py
mothpy/demo_thick_plume.py
mothpy/graphics_from_file.py
mothpy/job_generator.py
mothpy/kalman.py
mothpy/line_graphs.py
mothpy/line_graphs_qa.py
mothpy/moth_graphics.py
mothpy/mothpy_demos.py
mothpy/mothpy_models.py
mothpy/navigation_competition.py
mothpy/pompy_comparison.py
mothpy/shapes.py
mothpy/simulation.py
mothpy/statistics.py
mothpy/pompy/__init__.py
mothpy/pompy/demos.py
mothpy/pompy/models.py
mothpy/pompy/processors.py
mothpy/pompy/setup.py
mothpy-0.0.1.dist-info/LICENSE
mothpy-0.0.1.dist-info/METADATA
mothpy-0.0.1.dist-info/WHEEL
mothpy-0.0.1.dist-info/top_level.txt
mothpy-0.0.1.dist-info/RECORD
