Metadata-Version: 2.1
Name: mothpy
Version: 0.0.1
Summary: MothPy allows simulation moth-like navigators in dynamic 2D odour concentration fields spread in turbulent flows
Home-page: https://github.com/alexliberzonlab/mothpy
Author: Noam Benelli and Alex Liberzon
Author-email: alex.liberzon@gmail.com
License: UNKNOWN
Platform: UNKNOWN
Classifier: Programming Language :: Python :: 2.7
Classifier: License :: OSI Approved :: MIT License
Classifier: Operating System :: OS Independent
